statictorch/__init__.py
statictorch/__init__.pyi
statictorch-0.0.4.dist-info/LICENSE
statictorch-0.0.4.dist-info/METADATA
statictorch-0.0.4.dist-info/WHEEL
statictorch-0.0.4.dist-info/top_level.txt
statictorch-0.0.4.dist-info/RECORD
